pystallone-1.0.0b5.dist-info/RECORD
pystallone-1.0.0b5.dist-info/WHEEL
pystallone-1.0.0b5.dist-info/metadata.json
pystallone-1.0.0b5.dist-info/DESCRIPTION.rst
pystallone-1.0.0b5.dist-info/METADATA
pystallone-1.0.0b5.dist-info/top_level.txt
pystallone/_version.py
pystallone/__init__.py
pystallone/stallone-1.0-SNAPSHOT-jar-with-dependencies.jar
