Metadata-Version: 2.0
Name: pystallone
Version: 1.0.0b5
Summary: Python binding for Stallone java library
Home-page: http://bitbucket.org/cmb-fu/stallone
Author: Martin K. Scherer
Author-email: stallone@lists.fu-berlin.de
License: Simplified BSD License
Keywords: Markov modeling,Molecular trajectories analysis,MD
Platform: UNKNOWN
Classifier: Development Status :: 4 - Beta
Classifier: Environment :: Console
Classifier: Intended Audience :: Science/Research
Classifier: License :: OSI Approved :: BSD License
Classifier: Natural Language :: English
Classifier: Operating System :: MacOS :: MacOS X
Classifier: Operating System :: POSIX :: Linux
Classifier: Programming Language :: Java
Classifier: Programming Language :: Python :: 2.6
Classifier: Programming Language :: Python :: 2.7
Classifier: Programming Language :: Python :: 3
Classifier: Topic :: Scientific/Engineering :: Bio-Informatics
Classifier: Topic :: Scientific/Engineering :: Chemistry
Classifier: Topic :: Scientific/Engineering :: Mathematics
Classifier: Topic :: Scientific/Engineering :: Physics
Classifier: Topic :: Software Development :: Libraries :: Java Libraries
Requires-Dist: JPype1 (>=0.5.6)
Requires-Dist: numpy (>=1.6.0)
